LICENSE.txt
README.md
setup.py
tooldirectory/__init__.py
tooldirectory/tooldir.py
tooldirectory.egg-info/PKG-INFO
tooldirectory.egg-info/SOURCES.txt
tooldirectory.egg-info/dependency_links.txt
tooldirectory.egg-info/entry_points.txt
tooldirectory.egg-info/requires.txt
tooldirectory.egg-info/top_level.txt
tooldirectory/lib/__init__.py
tooldirectory/lib/core.py