Metadata-Version: 2.1
Name: tooldirectory
Version: 5.1.1
Summary: Dynamic visualization of softwares managed by a Bioinformatics Core Facility
Home-page: https://github.com/ifremer-bioinformatics/ToolDirectory
Author: Alexandre Cormier; Patrick Durand
Author-email: alexandre.cormier@ifremer.fr
Maintainer: Alexandre Cormier
Maintainer-email: alexandre.cormier@ifremer.fr
License: Apache 2.0
Classifier: Development Status :: 5 - Production/Stable
Classifier: Intended Audience :: Science/Research
Classifier: Topic :: Scientific/Engineering
Classifier: License :: OSI Approved :: Apache Software License
Classifier: Programming Language :: Python :: 3
Classifier: Programming Language :: Python :: 3.8
Requires-Python: >=3.8
License-File: LICENSE.txt
